fincheck/__init__.py
fincheck/checksum.py
fincheck/data.py
fincheck/extract.py
fincheck/utils.py
fincheck/validate.py
fincheck/refdata/.DS_Store
fincheck/refdata/cusip/.DS_Store
fincheck/refdata/cusip/cusip_list.csv
fincheck/refdata/cusip/cusip_ticker_map.csv
fincheck/refdata/isin/country_codes.csv
fincheck-0.0.5.dist-info/LICENSE
fincheck-0.0.5.dist-info/METADATA
fincheck-0.0.5.dist-info/WHEEL
fincheck-0.0.5.dist-info/top_level.txt
fincheck-0.0.5.dist-info/RECORD
