Metadata-Version: 2.1
Name: fincheck
Version: 0.0.5
Summary: Utilities to work with financial security identifiers, accounts, and checkdigit algorithms
Home-page: https://github.com/trevormcguire/fincheck
Author: Trevor McGuire
Author-email: trevormcguire13@gmail.com
License: UNKNOWN
Project-URL: Bug Tracker, https://github.com/trevormcguire/fincheck/issues
Platform: UNKNOWN
Classifier: Programming Language :: Python :: 3
Classifier: License :: OSI Approved :: MIT License
Classifier: Operating System :: OS Independent
Classifier: Development Status :: 3 - Alpha
Requires-Python: >=3.3
License-File: LICENSE
